pytibade/__init__.py
pytibade/pytibade.py
pytibade-1.0.0.dev1.data/data/LICENSE
pytibade-1.0.0.dev1.data/data/README.md
pytibade-1.0.0.dev1.dist-info/LICENSE
pytibade-1.0.0.dev1.dist-info/METADATA
pytibade-1.0.0.dev1.dist-info/WHEEL
pytibade-1.0.0.dev1.dist-info/entry_points.txt
pytibade-1.0.0.dev1.dist-info/top_level.txt
pytibade-1.0.0.dev1.dist-info/RECORD
