Metadata-Version: 2.1
Name: pytibade
Version: 1.0.0.dev1
Summary: Decrypt Titanium Backup for Android backups with Python/pycryptodome
Home-page: https://github.com/twlee79/py-tibade
Author: Tet Woo Lee
Author-email: developer@twlee.nz
License: UNKNOWN
Platform: UNKNOWN
Classifier: Programming Language :: Python :: 3
Classifier: License :: OSI Approved :: MIT License
Classifier: Operating System :: OS Independent
Requires-Dist: pycryptodome (>=v3.8.2)
